revealer/CheckGrid.c
revealer/CheckGrid.cpython-39-x86_64-linux-gnu.so
revealer/CheckGrid.pyx
revealer/DepMapToCCLE.py
revealer/MutMaker.c
revealer/MutMaker.cpython-39-x86_64-linux-gnu.so
revealer/MutMaker.pyx
revealer/MutMaker_multi.py
revealer/MutMaker_old.py
revealer/REVEALER.py
revealer/REVEALER_Cython.c
revealer/REVEALER_Cython.cpython-39-x86_64-linux-gnu.so
revealer/REVEALER_Cython.pyx
revealer/REVEALER_Cython_old.pyx
revealer/REVEALER_preprocess.py
revealer/REVEALER_runbenchmark.c
revealer/REVEALER_runbenchmark.cpython-39-x86_64-linux-gnu.so
revealer/REVEALER_runbenchmark.pyx
revealer/REVEALER_test.py
revealer/__init__.py
revealer/revealer.py
revealer/setup_cython.py
revealer/ccal/__init__.py
revealer/ccal/assign_colors.py
revealer/ccal/cluster_2d_array_rows.py
revealer/ccal/count_coclustering_and_normalize.py
revealer/ccal/decorate.py
revealer/ccal/dict_.py
revealer/ccal/hierarchical_cluster_distance_and_compute_ccc.py
revealer/ccal/multiprocess.py
revealer/ccal/nmf.py
revealer/ccal/nmf_consensus_cluster.py
revealer/ccal/nmf_consensus_cluster_with_multiple_k.py
revealer/ccal/normalize_1d_array.py
revealer/ccal/normalize_2d_array.py
revealer/ccal/path.py
revealer/ccal/plot_heatmap.py
revealer/ccal/plot_nmf.py
revealer/ccal/plot_points.py
revealer/ccal/save_plot.py
revealer/ccal/style.py
revealer/data/DepMapToCCLE.py
revealer/data/REVEALER_Example.ipynb
revealer/data/__init__.py
revealer/data/sample_input/CCLE_complete_sigs.gct
revealer/data/sample_input/NameConvert.csv
revealer/data/sample_input/TissueType_CCLE.gct
revealer/data/sample_input/__init__.py
revealer/data/sample_input/allgeneLocus.txt
revealer/data/sample_output/CCLE_NRF2_groudtruth.txt
revealer/data/sample_output/__init__.py
REVEALER-2.1.9.dist-info/LICENSE
REVEALER-2.1.9.dist-info/METADATA
REVEALER-2.1.9.dist-info/WHEEL
REVEALER-2.1.9.dist-info/entry_points.txt
REVEALER-2.1.9.dist-info/top_level.txt
REVEALER-2.1.9.dist-info/RECORD
