Metadata-Version: 2.1
Name: REVEALER
Version: 2.1.9
Summary: REVEALER#TODO
Home-page: https://github.com/yoshihiko1218/REVEALER
Author: Jiayan(Yoshii) Ma
Author-email: "Jiayan(Yoshii) Ma" <jim095@ucsd.edu>
License: MIT
Keywords: REVEALER
Classifier: Programming Language :: Python :: 3
Classifier: License :: OSI Approved :: MIT License
Classifier: Operating System :: OS Independent
Requires-Python: >=3.7, <3.10
License-File: LICENSE
Requires-Dist: pandas==1.2.1
Requires-Dist: Cython==0.29.21
Requires-Dist: numpy==1.22.4
Requires-Dist: matplotlib==3.4.0
Requires-Dist: seaborn==0.11.0
Requires-Dist: multiprocess==0.70.11
Requires-Dist: scipy>=1.7.0
Requires-Dist: tqdm==4.62.0
Requires-Dist: scikit-learn==1.3.2
Requires-Dist: requests==2.32.3
